pyxt/future.py
pyxt/spot.py
pyxt-0.1.1.dist-info/LICENSE
pyxt-0.1.1.dist-info/METADATA
pyxt-0.1.1.dist-info/WHEEL
pyxt-0.1.1.dist-info/top_level.txt
pyxt-0.1.1.dist-info/RECORD
