Metadata-Version: 2.1
Name: pyxt
Version: 0.1.1
Summary: Python3 XT.COM HTTP API Connector
Home-page: https://github.com/kelvinxue/pyxt
Author: kx
Author-email: kx@xt.com
License: MIT License
Keywords: xt api connector
Classifier: Development Status :: 4 - Beta
Classifier: Intended Audience :: Developers
Classifier: Topic :: Software Development :: Libraries :: Python Modules
Classifier: License :: OSI Approved :: MIT License
Classifier: Programming Language :: Python :: 3.9
Classifier: Programming Language :: Python :: 3.10
Requires-Python: >=3.9
License-File: LICENSE
Requires-Dist: requests
